README.txt
setup.py
getpaid/__init__.py
getpaid.recipe.release.egg-info/PKG-INFO
getpaid.recipe.release.egg-info/SOURCES.txt
getpaid.recipe.release.egg-info/dependency_links.txt
getpaid.recipe.release.egg-info/entry_points.txt
getpaid.recipe.release.egg-info/namespace_packages.txt
getpaid.recipe.release.egg-info/not-zip-safe
getpaid.recipe.release.egg-info/requires.txt
getpaid.recipe.release.egg-info/top_level.txt
getpaid/recipe/__init__.py
getpaid/recipe/release/__init__.py
getpaid/recipe/release/getpaidcorepackages.py
getpaid/recipe/release/tests/__init__.py
getpaid/recipe/release/tests/test_docs.py