Metadata-Version: 1.0
Name: getpaid.recipe.release
Version: 2.0
Summary: recipe for the releases of getpaid
Home-page: http://plonegetpaid.com/
Author: Lucie Lejard
Author-email: lucie@sixfeetup.com
License: ZPL
Platform: UNKNOWN
Classifier: Framework :: Plone
Classifier: Framework :: Zope3
Classifier: Intended Audience :: Developers
Classifier: Operating System :: OS Independent
Classifier: Programming Language :: Python
Classifier: Topic :: Software Development :: Build Tools
Classifier: Topic :: Office/Business :: Financial
Classifier: Topic :: Software Development :: Libraries :: Python Modules
Classifier: License :: OSI Approved :: Zope Public License
